squadro/__init__.py
squadro/agents/__init__.py
squadro/agents/agent.py
squadro/agents/alphabeta_agent.py
squadro/agents/best.py
squadro/agents/human_agent.py
squadro/agents/montecarlo_agent.py
squadro/agents/random_agent.py
squadro/algorithms/__init__.py
squadro/algorithms/minimax.py
squadro/animation/__init__.py
squadro/animation/animated_game.py
squadro/animation/board.py
squadro/animation/dynamic_board.py
squadro/core/__init__.py
squadro/core/benchmarking.py
squadro/core/game.py
squadro/evaluators/__init__.py
squadro/evaluators/evaluator.py
squadro/ml/__init__.py
squadro/ml/channels.py
squadro/ml/ml.py
squadro/resources/corner.png
squadro/resources/red_pawn.png
squadro/resources/red_pawn_fin.png
squadro/resources/red_pawn_ret.png
squadro/resources/start_1_b.png
squadro/resources/start_1_l.png
squadro/resources/start_1_r.png
squadro/resources/start_1_t.png
squadro/resources/start_2_b.png
squadro/resources/start_2_l.png
squadro/resources/start_2_r.png
squadro/resources/start_2_t.png
squadro/resources/start_3_b.png
squadro/resources/start_3_l.png
squadro/resources/start_3_r.png
squadro/resources/start_3_t.png
squadro/resources/tile.png
squadro/resources/yellow_pawn.png
squadro/resources/yellow_pawn_fin.png
squadro/resources/yellow_pawn_ret.png
squadro/state/__init__.py
squadro/state/state.py
squadro/state/evaluators/__init__.py
squadro/state/evaluators/advancement.py
squadro/state/evaluators/base.py
squadro/state/evaluators/constant.py
squadro/state/evaluators/ml.py
squadro/state/evaluators/rl.py
squadro/state/evaluators/rollout.py
squadro/tests/__init__.py
squadro/tests/base.py
squadro/tests/conftest.py
squadro/tests/agents/__init__.py
squadro/tests/agents/test_alphabeta_agent.py
squadro/tests/agents/test_human_agent.py
squadro/tests/agents/test_montecarlo_agent.py
squadro/tests/agents/test_random_agent.py
squadro/tests/animation/__init__.py
squadro/tests/animation/test_animation.py
squadro/tests/core/__init__.py
squadro/tests/core/test_game.py
squadro-1.0.3.dist-info/METADATA
squadro-1.0.3.dist-info/WHEEL
squadro-1.0.3.dist-info/top_level.txt
squadro-1.0.3.dist-info/RECORD
