Metadata-Version: 2.4
Name: squadro
Version: 1.0.3
Summary: Play the Squadro Board Game against Someone Else or an AI
Author: Martin
License-Expression: MIT
Project-URL: Homepage, https://github.com/MartinBraquet/squadro
Project-URL: Bug Tracker, https://github.com/MartinBraquet/squadro/issues
Classifier: Programming Language :: Python :: 3
Classifier: Operating System :: OS Independent
Requires-Python: >=3.11
Requires-Dist: Pillow
Requires-Dist: ipython
Requires-Dist: igraph
Requires-Dist: matplotlib
Requires-Dist: numpy
Requires-Dist: pandas
Requires-Dist: plotly
Requires-Dist: pydantic
Requires-Dist: pygame
Requires-Dist: torch
Provides-Extra: all
Requires-Dist: squadro[dev,testing]; extra == "all"
Provides-Extra: dev
Requires-Dist: black; extra == "dev"
Requires-Dist: isort; extra == "dev"
Requires-Dist: flake8; extra == "dev"
Requires-Dist: flake8-pyproject; extra == "dev"
Requires-Dist: nox; extra == "dev"
Requires-Dist: notebook; extra == "dev"
Requires-Dist: pip-tools; extra == "dev"
Requires-Dist: build; extra == "dev"
Provides-Extra: testing
Requires-Dist: pytest; extra == "testing"
Requires-Dist: pytest-cov; extra == "testing"
Requires-Dist: pytest-env; extra == "testing"
Requires-Dist: pytest-html; extra == "testing"
